{
  "$schema": "https://developer.microsoft.com/json-schemas/fabric/item/report/definition/visualContainer/2.4.0/schema.json",
  "name": "cfe0e756ad79bc0e1e7d",
  "position": {
    "x": 339.63699222126189,
    "y": 314.19187554019015,
    "z": 5000,
    "height": 82.973206568712186,
    "width": 128.33189282627484
  },
  "visual": {
    "visualType": "PBI_CV_25997FEB_F466_44FA_B562_AC4063283C4C",
    "query": {
      "queryState": {
        "axis": {
          "projections": [
            {
              "field": {
                "Column": {
                  "Expression": {
                    "SourceRef": {
                      "Entity": "dCalendario"
                    }
                  },
                  "Property": "Nome do Mês"
                }
              },
              "queryRef": "dCalendario.Nome do Mês"
            }
          ]
        },
        "measure": {
          "projections": [
            {
              "field": {
                "Measure": {
                  "Expression": {
                    "SourceRef": {
                      "Entity": "Medidas"
                    }
                  },
                  "Property": "37 Visao America do Norte"
                }
              },
              "queryRef": "Medidas.37 Visao America do Norte"
            }
          ]
        }
      }
    },
    "objects": {
      "label": [
        {
          "properties": {
            "show": {
              "expr": {
                "Literal": {
                  "Value": "false"
                }
              }
            }
          }
        }
      ],
      "area": [
        {
          "properties": {
            "show": {
              "expr": {
                "Literal": {
                  "Value": "true"
                }
              }
            },
            "fill": {
              "solid": {
                "color": {
                  "expr": {
                    "ThemeDataColor": {
                      "ColorId": 9,
                      "Percent": 0
                    }
                  }
                }
              }
            }
          }
        }
      ],
      "line": [
        {
          "properties": {
            "kind": {
              "expr": {
                "Literal": {
                  "Value": "'cardinal'"
                }
              }
            },
            "weight": {
              "expr": {
                "Literal": {
                  "Value": "2L"
                }
              }
            },
            "fill": {
              "solid": {
                "color": {
                  "expr": {
                    "ThemeDataColor": {
                      "ColorId": 9,
                      "Percent": 0
                    }
                  }
                }
              }
            }
          }
        }
      ]
    },
    "visualContainerObjects": {
      "background": [
        {
          "properties": {
            "show": {
              "expr": {
                "Literal": {
                  "Value": "false"
                }
              }
            }
          }
        }
      ]
    },
    "drillFilterOtherVisuals": true
  }
}